executor.py
rabbitmqcli/__init__.py
rabbitmqcli/connection.py
rabbitmqcli/modules/__init__.py
rabbitmqcli/modules/bindings.py
rabbitmqcli/modules/exchanges.py
rabbitmqcli/modules/queues.py
rabbitmqcli/modules/vhosts.py
rabbitmqcli/utils/__init__.py
rabbitmqcli/utils/config.py
rabbitmqcli/utils/secrets.py
rabbitmq_cli-0.0.1.dist-info/LICENSE
rabbitmq_cli-0.0.1.dist-info/METADATA
rabbitmq_cli-0.0.1.dist-info/WHEEL
rabbitmq_cli-0.0.1.dist-info/entry_points.txt
rabbitmq_cli-0.0.1.dist-info/top_level.txt
rabbitmq_cli-0.0.1.dist-info/RECORD
