Metadata-Version: 2.1
Name: rabbitmq-cli
Version: 0.0.1
Summary: <short description for the tool>
Home-page: https://github.com/brianou7/rabbitmqcli
Author: Brahian Ocampo
Author-email: baocampo@bancolombia.com.co
License: GNU General Public License v3.0
Classifier: Programming Language :: Python :: 3.9
Classifier: Operating System :: OS Independent
Requires-Python: >=3.9
License-File: LICENSE
Requires-Dist: boto3 ==1.28.23
Requires-Dist: click ==8.1.6
Requires-Dist: pika ==1.3.2
Requires-Dist: requests ==2.31.0
Requires-Dist: rich ==13.5.2
